sensapex/__init__.py
sensapex/accuracy_test.py
sensapex/libum.dll
sensapex/pressure_test.py
sensapex/sensapex.py
sensapex/test.py
sensapex/umpcli.exe
sensapex/utils.py
sensapex-1.400.4.dist-info/licenses/LICENSE
tests/__init__.py
tests/test_move_request.py
sensapex-1.400.4.dist-info/METADATA
sensapex-1.400.4.dist-info/WHEEL
sensapex-1.400.4.dist-info/top_level.txt
sensapex-1.400.4.dist-info/RECORD
